eodhd_py/__init__.py
eodhd_py/base.py
eodhd_py/client.py
eodhd_py/costs.py
eodhd_py/eod_historical.py
eodhd_py/intraday_historical.py
eodhd_py/py.typed
eodhd_py/user.py
eodhd_py/utils.py
eodhd_py-0.3.0.dist-info/WHEEL
eodhd_py-0.3.0.dist-info/METADATA
eodhd_py-0.3.0.dist-info/RECORD
