Metadata-Version: 2.3
Name: eodhd-py
Version: 0.3.0
Summary: Python Implementation for EODHD API
Requires-Dist: aiohttp>=3.12.15
Requires-Dist: pandas>=2.0.0
Requires-Dist: pydantic>=2.11.7
Requires-Dist: steindamm>=0.8.0
Requires-Python: >=3.13
